
{
  "boutiques": [
    {
      "type": "Feature",
      "geometry": {
        "type": "Point",
        "coordinates": [
          1.1900854110717773,
          6.180278245260716
        ]
      },
      "properties": {
        "id": "1",
        "nom": "Dagbe Dagbe",
        "proprietaire": "Kossi Juliano",
        "address":"mes adresse",
        "telephone":"0088255585"
      }
      
    },
    {
      "type": "Feature",
      "geometry": {
        "type": "Point",
        "coordinates": [
          1.1911582946777344,
          6.191627259167388
        ]
      },
      "properties": {
        "id": "2",
        "nom": "Manu Mava",
        "proprietaire": "Santrinos Afuto",
        "address":"Agoe 2 lions adresse",
        "telephone":"55891444"
      }
      
    },
    {
      "type": "Feature",
      "geometry": {
        "type": "Point",
        "coordinates": [
          1.19582946777344,
          6.1927259167388
        ]
      },
      "properties": {
        "id": "3",
        "nom": "Valentinattaire Position",
        "proprietaire": "Anna Noel",
        "address":"mes rue sekle",
        "telephone":"566628"
      }
      
    }
  ]
}
